ultrasound_acquisition_configuration/__init__.py
ultrasound_acquisition_configuration/__init__.pyi
ultrasound_acquisition_configuration/bindings.cpython-311-x86_64-linux-musl.so
ultrasound_acquisition_configuration/bindings.pyi
ultrasound_acquisition_configuration/libstdc++.so.6
ultrasound_acquisition_configuration/py.typed
ultrasound_acquisition_configuration/include/Uac-1.3.2_static/uac/acquisition.h
ultrasound_acquisition_configuration/include/Uac-1.3.2_static/uac/dataset.h
ultrasound_acquisition_configuration/include/Uac-1.3.2_static/uac/destination_link.h
ultrasound_acquisition_configuration/include/Uac-1.3.2_static/uac/element.h
ultrasound_acquisition_configuration/include/Uac-1.3.2_static/uac/element_geometry.h
ultrasound_acquisition_configuration/include/Uac-1.3.2_static/uac/enums.h
ultrasound_acquisition_configuration/include/Uac-1.3.2_static/uac/event.h
ultrasound_acquisition_configuration/include/Uac-1.3.2_static/uac/excitation.h
ultrasound_acquisition_configuration/include/Uac-1.3.2_static/uac/group.h
ultrasound_acquisition_configuration/include/Uac-1.3.2_static/uac/hw_config.h
ultrasound_acquisition_configuration/include/Uac-1.3.2_static/uac/igroup.h
ultrasound_acquisition_configuration/include/Uac-1.3.2_static/uac/impulse_response.h
ultrasound_acquisition_configuration/include/Uac-1.3.2_static/uac/probe.h
ultrasound_acquisition_configuration/include/Uac-1.3.2_static/uac/receive_setup.h
ultrasound_acquisition_configuration/include/Uac-1.3.2_static/uac/super_group.h
ultrasound_acquisition_configuration/include/Uac-1.3.2_static/uac/transform.h
ultrasound_acquisition_configuration/include/Uac-1.3.2_static/uac/transmit_setup.h
ultrasound_acquisition_configuration/include/Uac-1.3.2_static/uac/trigger.h
ultrasound_acquisition_configuration/include/Uac-1.3.2_static/uac/uac.h
ultrasound_acquisition_configuration/include/Uac-1.3.2_static/uac/vector.h
ultrasound_acquisition_configuration/include/Uac-1.3.2_static/uac/version.h
ultrasound_acquisition_configuration-1.3.2.dist-info/METADATA
ultrasound_acquisition_configuration-1.3.2.dist-info/WHEEL
ultrasound_acquisition_configuration-1.3.2.dist-info/top_level.txt
ultrasound_acquisition_configuration-1.3.2.dist-info/RECORD
ultrasound_acquisition_configuration-1.3.2.dist-info/sboms/auditwheel.cdx.json
