Metadata-Version: 2.1
Name: ultrasound-acquisition-configuration
Version: 1.3.2
Summary: Ultrasound Acquisition Configuration file format C++ implementation and wrapping in Python and Matlab
License: MIT License
Project-URL: Homepage, https://moduleus.com
Project-URL: Documentation, https://github.com/moduleus/uac/wiki
Project-URL: Repository, https://github.com/moduleus/uac.git
Project-URL: Issues, https://github.com/moduleus/uac/issues
Project-URL: Changelog, https://github.com/moduleus/uac/wiki/changelog
Classifier: Development Status :: 5 - Production/Stable
Classifier: Intended Audience :: Healthcare Industry
Classifier: Intended Audience :: Science/Research
Classifier: License :: OSI Approved :: MIT License
Classifier: Operating System :: Microsoft
Classifier: Operating System :: Unix
Classifier: Programming Language :: C++
Classifier: Programming Language :: Python :: 3 :: Only
Classifier: Programming Language :: Python :: 3.10
Classifier: Programming Language :: Python :: 3.11
Classifier: Programming Language :: Python :: 3.12
Classifier: Programming Language :: Python :: 3.8
Classifier: Programming Language :: Python :: 3.9
Classifier: Programming Language :: Python :: 3
Classifier: Programming Language :: Python :: Implementation :: CPython
Classifier: Programming Language :: Python :: Implementation :: PyPy
Classifier: Programming Language :: Python
Classifier: Topic :: File Formats
Classifier: Topic :: Scientific/Engineering
Requires-Python: >=3.8
Requires-Dist: cmake-build-extension==0.6.1
Requires-Dist: parameterized==0.9.0
Requires-Dist: cmake==3.31.1
Requires-Dist: gitdb==4.0.11
Requires-Dist: GitPython==3.1.43
Requires-Dist: ninja==1.11.1.2
Requires-Dist: packaging
Requires-Dist: setuptools-scm==8.1.0
Requires-Dist: smmap==5.0.1
Requires-Dist: numpy==2.1.3; python_version == "3.10"
Requires-Dist: numpy==1.24.4; python_version == "3.8"
Requires-Dist: setuptools==75.3.0; python_version == "3.8"
Requires-Dist: numpy==1.26.4; python_version == "3.9"
Requires-Dist: numpy==2.3.4; python_version >= "3.11"
Requires-Dist: setuptools==75.6.0; python_version >= "3.9"
